{
  "name": "Arming Sword (Steel)",
  "slot": "Weapon",
  "layers": {
    "main": {
      "zPos": 140,
      "paths": {
        "male": "weapons/sword/arming/universal/fg/",
        "female": "weapons/sword/arming/universal/fg/"
      }
    },
    "behind": {
      "zPos": 9,
      "paths": {
        "male": "weapons/sword/arming/universal/bg/",
        "female": "weapons/sword/arming/universal/bg/"
      }
    },
    "slash_behind": {
      "custom_animation": "slash_oversize",
      "zPos": -1,
      "paths": {
        "male": "weapons/sword/arming/attack_slash/bg/",
        "female": "weapons/sword/arming/attack_slash/bg/"
      }
    },
    "slash_front": {
      "custom_animation": "slash_oversize",
      "zPos": 150,
      "paths": {
        "male": "weapons/sword/arming/attack_slash/fg/",
        "female": "weapons/sword/arming/attack_slash/fg/"
      }
    }
  },
  "variants": ["steel", "iron", "gold"],
  "animations": ["walk", "idle", "slash_oversize", "thrust_oversize"],
  "preview_row": 10,
  "preview_column": 1
}
